konsync/__init__.py
konsync/__main__.py
konsync/conf_kde.taml
konsync/conf_other.taml
konsync/consts.py
konsync/funcs.py
konsync/parse.py
konsync-0.2.1.dist-info/LICENSE
konsync-0.2.1.dist-info/METADATA
konsync-0.2.1.dist-info/WHEEL
konsync-0.2.1.dist-info/entry_points.txt
konsync-0.2.1.dist-info/top_level.txt
konsync-0.2.1.dist-info/RECORD
