Metadata-Version: 2.1
Name: konsync
Version: 0.2.1
Summary: A program that lets you sync your Plasma configuration to a synced folder. (Seafile, Nextcloud, etc.)
Author-email: EpicStuff <EpicStuff@users.noreply.github.com>
Project-URL: Homepage, https://github.com/EpicStuff/konsync
Project-URL: Issues, https://github.com/EpicStuff/konsync/issues
Classifier: Operating System :: OS Independent
Classifier: Programming Language :: Python :: 3
Requires-Python: >=3.10
License-File: LICENSE
Requires-Dist: taml
Requires-Dist: Send2Trash
Requires-Dist: epicstuff
